nagra_network_misc_utils/__init__.py
nagra_network_misc_utils/__main__.py
nagra_network_misc_utils/backend_checker/__init__.py
nagra_network_misc_utils/backend_checker/__main__.py
nagra_network_misc_utils/gitlab.py
nagra_network_misc_utils/logger/__init__.py
nagra_network_misc_utils/logger/colored_formatter.py
nagra_network_misc_utils/logger/logger.py
nagra_network_misc_utils-0.2.7.dist-info/METADATA
nagra_network_misc_utils-0.2.7.dist-info/WHEEL
nagra_network_misc_utils-0.2.7.dist-info/entry_points.txt
nagra_network_misc_utils-0.2.7.dist-info/RECORD
