Metadata-Version: 2.1
Name: nagra_network_misc_utils
Version: 0.2.7
Summary: Miscelleanous utilities for pipeline management
Author: David Gallay
Author-email: david.gallay@nagra.com
Requires-Python: >=3.9.0,<4.0.0
Classifier: Programming Language :: Python :: 3
Classifier: Programming Language :: Python :: 3.9
Classifier: Programming Language :: Python :: 3.10
Classifier: Programming Language :: Python :: 3.11
Classifier: Programming Language :: Python :: 3.12
Requires-Dist: click (>=8.1.7,<9.0.0)
Requires-Dist: colorama (>=0.4.6,<0.5.0)
Requires-Dist: gitpython (>=3.1.43,<4.0.0)
Requires-Dist: python-gitlab (>=4.10.0,<5.0.0)
Requires-Dist: rich (>=13.6.0,<14.0.0)
